CHANGES.txt
README.txt
bootstrap.py
buildout.cfg
setup.py
src/hurry/__init__.py
src/hurry.datatables.egg-info/PKG-INFO
src/hurry.datatables.egg-info/SOURCES.txt
src/hurry.datatables.egg-info/dependency_links.txt
src/hurry.datatables.egg-info/entry_points.txt
src/hurry.datatables.egg-info/namespace_packages.txt
src/hurry.datatables.egg-info/not-zip-safe
src/hurry.datatables.egg-info/requires.txt
src/hurry.datatables.egg-info/top_level.txt
src/hurry/datatables/__init__.py
src/hurry/datatables/datatables.txt
src/hurry/datatables/tests.py
src/hurry/datatables/datatables-build/extras/AutoFill/callbacks.html
src/hurry/datatables/datatables-build/extras/AutoFill/columns.html
src/hurry/datatables/datatables-build/extras/AutoFill/index.html
src/hurry/datatables/datatables-build/extras/AutoFill/inputs.html
src/hurry/datatables/datatables-build/extras/AutoFill/scrolling.html
src/hurry/datatables/datatables-build/extras/AutoFill/media/css/AutoFill.css
src/hurry/datatables/datatables-build/extras/AutoFill/media/docs/files.html
src/hurry/datatables/datatables-build/extras/AutoFill/media/docs/index.html
src/hurry/datatables/datatables-build/extras/AutoFill/media/docs/css/default.css
src/hurry/datatables/datatables-build/extras/AutoFill/media/docs/symbols/AutoFill#dom.html
src/hurry/datatables/datatables-build/extras/AutoFill/media/docs/symbols/AutoFill#s.border.html
src/hurry/datatables/datatables-build/extras/AutoFill/media/docs/symbols/AutoFill#s.columns.html
src/hurry/datatables/datatables-build/extras/AutoFill/media/docs/symbols/AutoFill#s.drag.html
src/hurry/datatables/datatables-build/extras/AutoFill/media/docs/symbols/AutoFill#s.filler.html
src/hurry/datatables/datatables-build/extras/AutoFill/media/docs/symbols/AutoFill#s.html
src/hurry/datatables/datatables-build/extras/AutoFill/media/docs/symbols/AutoFill#s.screen.html
src/hurry/datatables/datatables-build/extras/AutoFill/media/docs/symbols/AutoFill#s.scroller.html
src/hurry/datatables/datatables-build/extras/AutoFill/media/docs/symbols/AutoFill.html
src/hurry/datatables/datatables-build/extras/AutoFill/media/docs/symbols/_global_.html
src/hurry/datatables/datatables-build/extras/AutoFill/media/docs/symbols/src/js_AutoFill.js.html
src/hurry/datatables/datatables-build/extras/AutoFill/media/images/filler.png
