Metadata-Version: 1.0
Name: hurry.datatables
Version: 1.7.6
Summary: hurry.resource style resources for jQuery datatables.
Home-page: UNKNOWN
Author: Martijn Faassen
Author-email: faassen@startifact.com
License: BSD
Keywords: hurry.resource jquery
Platform: UNKNOWN
